{
	"1": {
		"id": "2025-03-01",
		"type": "quartetos",
		"number": 1,
		"difficulty": 1,
		"grid": [
			"537",
			"1409",
			"886",
			"880",
			"270",
			"642",
			"400",
			"1410",
			"357",
			"165",
			"1411",
			"342",
			"1412",
			"55",
			"2680",
			"1495"
		],
		"setId": "91d4f;;a4bcd;;bafda;;105f6",
		"sets": [
			{
				"id": "a4bcd",
				"itemsIds": ["537", "342", "886", "642"],
				"title": "Coisas com cabos",
				"level": 3
			},
			{
				"title": "Peças",
				"itemsIds": ["880", "400", "270", "165"],
				"level": 2,
				"id": "91d4f"
			},
			{
				"id": "105f6",
				"title": "Vidro",
				"level": 1,
				"itemsIds": ["357", "55", "2680", "1495"]
			},
			{
				"title": "Danças",
				"itemsIds": ["1411", "1412", "1409", "1410"],
				"level": 0,
				"id": "bafda"
			}
		]
	},
	"2": {
		"id": "2025-03-02",
		"type": "quartetos",
		"number": 2,
		"difficulty": 1,
		"grid": [
			"2379",
			"21",
			"269",
			"537",
			"1091",
			"1248",
			"316",
			"2373",
			"629",
			"198",
			"5",
			"36",
			"1957",
			"1602",
			"1795",
			"940"
		],
		"setId": "2150b;;8b326;;c5076;;27437",
		"sets": [
			{
				"title": "Animais com chifres",
				"itemsIds": ["1957", "1091", "940", "1248"],
				"id": "2150b",
				"level": 0
			},
			{
				"level": 1,
				"title": "Limpeza",
				"itemsIds": ["1795", "537", "2379", "2373"],
				"id": "27437"
			},
			{
				"title": "Na fazenda",
				"itemsIds": ["5", "198", "1602", "36"],
				"id": "8b326",
				"level": 2
			},
			{
				"title": "Construção",
				"level": 3,
				"itemsIds": ["316", "269", "21", "629"],
				"id": "c5076"
			}
		]
	},
	"3": {
		"id": "2025-03-03",
		"type": "quartetos",
		"number": 3,
		"difficulty": 1,
		"grid": [
			"912",
			"2552",
			"182",
			"42",
			"84",
			"22",
			"285",
			"1451",
			"122",
			"425",
			"350",
			"823",
			"761",
			"341",
			"2578",
			"178"
		],
		"setId": "8942f;;ccbd3;;32336;;174d4",
		"sets": [
			{
				"title": "Ovo",
				"id": "32336",
				"level": 0,
				"itemsIds": ["761", "2578", "2552", "42"]
			},
			{
				"title": "Hora de dormir",
				"id": "174d4",
				"level": 1,
				"itemsIds": ["912", "22", "823", "1451"]
			},
			{
				"itemsIds": ["285", "425", "122", "182"],
				"level": 3,
				"id": "8942f",
				"title": "Triângulos"
			},
			{
				"level": 2,
				"title": "Coisas transparentes",
				"itemsIds": ["178", "84", "350", "341"],
				"id": "ccbd3"
			}
		]
	},
	"4": {
		"id": "2025-03-04",
		"type": "quartetos",
		"number": 4,
		"difficulty": 2,
		"grid": [
			"127",
			"672",
			"947",
			"497",
			"1234",
			"436",
			"479",
			"1579",
			"2382",
			"589",
			"1142",
			"1036",
			"1145",
			"9",
			"227",
			"2118"
		],
		"setId": "7034d;;8163b;;35b37;;832c5",
		"sets": [
			{
				"itemsIds": ["479", "2118", "497", "127"],
				"id": "7034d",
				"title": "Formato de Pirâmide",
				"level": 3
			},
			{
				"level": 2,
				"itemsIds": ["947", "589", "227", "1036"],
				"title": "Armas sem bala",
				"id": "8163b"
			},
			{
				"title": "Cozinhando",
				"itemsIds": ["2382", "1234", "1145", "436"],
				"level": 1,
				"id": "832c5"
			},
			{
				"itemsIds": ["1142", "1579", "9", "672"],
				"id": "35b37",
				"title": "Dentário",
				"level": 0
			}
		]
	},
	"5": {
		"id": "2025-03-05",
		"type": "quartetos",
		"number": 5,
		"difficulty": 1,
		"grid": [
			"2707",
			"1310",
			"197",
			"915",
			"57",
			"1451",
			"2739",
			"218",
			"348",
			"334",
			"398",
			"349",
			"823",
			"826",
			"381",
			"425"
		],
		"setId": "16b22;;4c5b5;;696f1;;174d4",
		"sets": [
			{
				"title": "Quarto",
				"itemsIds": ["823", "1310", "915", "1451"],
				"id": "174d4",
				"level": 1
			},
			{
				"id": "16b22",
				"level": 0,
				"title": "Neve",
				"itemsIds": ["2739", "349", "2707", "348"]
			},
			{
				"level": 2,
				"id": "4c5b5",
				"title": "Proteja-se dos raios UVB",
				"itemsIds": ["57", "197", "826", "218"]
			},
			{
				"id": "696f1",
				"title": "Metal",
				"itemsIds": ["425", "398", "381", "334"],
				"level": 3
			}
		]
	},
	"6": {
		"id": "2025-03-06",
		"type": "quartetos",
		"number": 6,
		"difficulty": 2,
		"grid": [
			"336",
			"184",
			"246",
			"20",
			"31",
			"205",
			"2243",
			"2242",
			"721",
			"263",
			"2246",
			"201",
			"768",
			"378",
			"2245",
			"1403"
		],
		"setId": "8e3d1;;09f58;;29b60;;528cd",
		"sets": [
			{
				"level": 2,
				"title": "Anos 90",
				"id": "29b60",
				"itemsIds": ["263", "205", "721", "184"]
			},
			{
				"itemsIds": ["1403", "201", "336", "768"],
				"title": "No cinema",
				"id": "8e3d1",
				"level": 1
			},
			{
				"title": "Continentes",
				"id": "09f58",
				"itemsIds": ["2245", "2242", "2246", "2243"],
				"level": 0
			},
			{
				"itemsIds": ["20", "246", "378", "31"],
				"level": 3,
				"title": "Feriados",
				"id": "528cd"
			}
		]
	},
	"7": {
		"id": "2025-03-07",
		"type": "quartetos",
		"number": 7,
		"difficulty": 1,
		"grid": [
			"1416",
			"1415",
			"525",
			"360",
			"248",
			"115",
			"39",
			"2600",
			"1217",
			"145",
			"1097",
			"442",
			"821",
			"1414",
			"443",
			"271"
		],
		"setId": "040b2;;2f8c3;;27bf3;;91818",
		"sets": [
			{
				"level": 0,
				"id": "040b2",
				"title": "Catástrofes",
				"itemsIds": ["2600", "1415", "1416", "1414"]
			},
			{
				"level": 1,
				"id": "91818",
				"title": "Brinquedos",
				"itemsIds": ["1217", "821", "145", "1097"]
			},
			{
				"id": "2f8c3",
				"level": 2,
				"itemsIds": ["442", "525", "443", "360"],
				"title": "Hora de dormir"
			},
			{
				"id": "27bf3",
				"itemsIds": ["115", "271", "248", "39"],
				"title": "Os elementos",
				"level": 3
			}
		]
	},
	"8": {
		"id": "2025-03-08",
		"type": "quartetos",
		"number": 8,
		"difficulty": 2,
		"grid": [
			"605",
			"355",
			"1821",
			"223",
			"125",
			"2799",
			"9",
			"169",
			"124",
			"581",
			"1844",
			"382",
			"1731",
			"379",
			"1352",
			"748"
		],
		"setId": "f0759;;be0b2;;366ba;;5221f",
		"sets": [
			{
				"itemsIds": ["124", "379", "382", "581"],
				"level": 0,
				"title": "Papel",
				"id": "be0b2"
			},
			{
				"itemsIds": ["9", "169", "223", "605"],
				"title": "Idosos",
				"id": "f0759",
				"level": 1
			},
			{
				"id": "366ba",
				"itemsIds": ["355", "748", "1352", "2799"],
				"title": "Garrafas alcoólicas",
				"level": 2
			},
			{
				"id": "5221f",
				"level": 3,
				"itemsIds": ["125", "1821", "1844", "1731"],
				"title": "Frutas"
			}
		]
	},
	"9": {
		"id": "2025-03-09",
		"type": "quartetos",
		"number": 9,
		"difficulty": 2,
		"grid": [
			"66",
			"233",
			"197",
			"2",
			"554",
			"116",
			"903",
			"867",
			"425",
			"826",
			"1285",
			"97",
			"458",
			"34",
			"418",
			"81"
		],
		"setId": "f277f;;8ee16;;7aa56;;fd96c",
		"sets": [
			{
				"level": 0,
				"id": "7aa56",
				"itemsIds": ["458", "867", "903", "1285"],
				"title": "Animais australianos"
			},
			{
				"level": 1,
				"title": "Na praia",
				"id": "f277f",
				"itemsIds": ["2", "197", "554", "826"]
			},
			{
				"id": "8ee16",
				"title": "Zoológico",
				"itemsIds": ["81", "97", "116", "233"],
				"level": 2
			},
			{
				"level": 3,
				"title": "Metal",
				"itemsIds": ["425", "418", "66", "34"],
				"id": "fd96c"
			}
		]
	},
	"10": {
		"id": "2025-03-10",
		"type": "quartetos",
		"number": 10,
		"difficulty": 2,
		"grid": [
			"672",
			"604",
			"393",
			"152",
			"395",
			"154",
			"922",
			"162",
			"918",
			"817",
			"526",
			"300",
			"649",
			"288",
			"153",
			"816"
		],
		"setId": "8340b;;83bbe;;cf614;;360d5",
		"sets": [
			{
				"level": 0,
				"title": "Animais super-heróis",
				"id": "8340b",
				"itemsIds": ["153", "162", "300", "526"]
			},
			{
				"id": "83bbe",
				"level": 1,
				"itemsIds": ["672", "816", "817", "922"],
				"title": "Vem num recipiente"
			},
			{
				"itemsIds": ["152", "154", "918", "395"],
				"title": "Eletrodomésticos",
				"id": "cf614",
				"level": 2
			},
			{
				"id": "360d5",
				"level": 3,
				"itemsIds": ["393", "649", "288", "604"],
				"title": "Na cozinha"
			}
		]
	},
	"11": {
		"id": "2025-03-11",
		"type": "quartetos",
		"number": 11,
		"difficulty": 2,
		"grid": [
			"80",
			"2176",
			"120",
			"141",
			"1094",
			"13",
			"682",
			"1967",
			"44",
			"159",
			"287",
			"583",
			"1256",
			"222",
			"22",
			"277"
		],
		"setId": "9a5db;;ef902;;764a0;;7892e",
		"sets": [
			{
				"itemsIds": ["44", "159", "277", "1094"],
				"level": 0,
				"title": "Pular",
				"id": "9a5db"
			},
			{
				"id": "ef902",
				"title": "Valioso",
				"itemsIds": ["13", "80", "120", "141"],
				"level": 1
			},
			{
				"id": "764a0",
				"title": "Apimentar a relação",
				"itemsIds": ["22", "222", "583", "682"],
				"level": 2
			},
			{
				"title": "Tempo",
				"id": "7892e",
				"level": 3,
				"itemsIds": ["2176", "287", "1967", "1256"]
			}
		]
	},
	"12": {
		"id": "2025-03-12",
		"type": "quartetos",
		"number": 12,
		"difficulty": 2,
		"grid": [
			"406",
			"1521",
			"500",
			"1515",
			"256",
			"337",
			"2460",
			"51",
			"22",
			"1516",
			"599",
			"538",
			"123",
			"1684",
			"110",
			"392"
		],
		"setId": "9919f;;23d22;;af33c;;80010",
		"sets": [
			{
				"itemsIds": ["51", "110", "500", "2460"],
				"title": "Devagar",
				"id": "9919f",
				"level": 0
			},
			{
				"level": 1,
				"itemsIds": ["337", "392", "538", "599"],
				"id": "af33c",
				"title": "Gastar"
			},
			{
				"id": "23d22",
				"level": 2,
				"itemsIds": ["1515", "1516", "1521", "1684"],
				"title": "Solzinho na paisagem"
			},
			{
				"level": 3,
				"title": "Mulheres",
				"id": "80010",
				"itemsIds": ["406", "123", "22", "256"]
			}
		]
	},
	"13": {
		"id": "2025-03-13",
		"type": "quartetos",
		"number": 13,
		"difficulty": 1,
		"grid": [
			"1925",
			"681",
			"167",
			"477",
			"2333",
			"540",
			"219",
			"505",
			"216",
			"1805",
			"245",
			"27",
			"179",
			"2201",
			"2334",
			"580"
		],
		"setId": "c4fe9;;20d49;;bd8ff;;15b25",
		"sets": [
			{
				"level": 0,
				"title": "Calçado de cano alto",
				"itemsIds": ["540", "2201", "2333", "2334"],
				"id": "c4fe9"
			},
			{
				"title": "Duas rodas",
				"level": 1,
				"id": "20d49",
				"itemsIds": ["27", "167", "179", "580"]
			},
			{
				"title": "Viagem",
				"id": "bd8ff",
				"level": 2,
				"itemsIds": ["219", "245", "477", "681"]
			},
			{
				"level": 3,
				"itemsIds": ["1805", "216", "505", "1925"],
				"id": "15b25",
				"title": "Asiático"
			}
		]
	},
	"14": {
		"id": "2025-03-14",
		"type": "quartetos",
		"number": 14,
		"difficulty": 2,
		"grid": [
			"338",
			"79",
			"167",
			"1124",
			"530",
			"478",
			"115",
			"655",
			"618",
			"1267",
			"1155",
			"654",
			"1737",
			"1402",
			"27",
			"26"
		],
		"setId": "9eab4;;1649b;;bf8fc;;d47b5",
		"sets": [
			{
				"itemsIds": ["1155", "1267", "1402", "1737"],
				"level": 0,
				"id": "bf8fc",
				"title": "Tem coração"
			},
			{
				"level": 1,
				"id": "9eab4",
				"title": "Jogando pedra-papel-tesoura",
				"itemsIds": ["115", "478", "530", "618"]
			},
			{
				"title": "Comendo porcaria",
				"id": "1649b",
				"level": 2,
				"itemsIds": ["79", "338", "654", "655"]
			},
			{
				"itemsIds": ["26", "27", "1124", "167"],
				"level": 3,
				"title": "Adolescentes",
				"id": "d47b5"
			}
		]
	},
	"15": {
		"id": "2025-03-15",
		"type": "quartetos",
		"number": 15,
		"difficulty": 2,
		"grid": [
			"1620",
			"83",
			"185",
			"206",
			"230",
			"303",
			"365",
			"219",
			"27",
			"507",
			"474",
			"1248",
			"314",
			"26",
			"1124",
			"429"
		],
		"setId": "6ad61;;7b2cf;;14a29;;d47b5",
		"sets": [
			{
				"level": 0,
				"itemsIds": ["219", "230", "429", "474"],
				"title": "Vôo",
				"id": "14a29"
			},
			{
				"id": "6ad61",
				"level": 1,
				"itemsIds": ["185", "507", "1248", "1620"],
				"title": "Coisas do papai noel"
			},
			{
				"title": "Sopro",
				"level": 2,
				"id": "7b2cf",
				"itemsIds": ["206", "303", "314", "365"]
			},
			{
				"title": "Adolescentes",
				"id": "d47b5",
				"itemsIds": ["1124", "26", "83", "27"],
				"level": 3
			}
		]
	},
	"16": {
		"id": "2025-03-16",
		"type": "quartetos",
		"number": 16,
		"difficulty": 1,
		"grid": [
			"588",
			"2408",
			"1539",
			"173",
			"553",
			"2032",
			"1484",
			"1592",
			"1598",
			"405",
			"127",
			"1627",
			"856",
			"814",
			"1501",
			"934"
		],
		"setId": "43a8d;;05a13;;8be52;;7654f",
		"sets": [
			{
				"title": "anfíbios",
				"level": 0,
				"itemsIds": ["856", "1598", "1627", "2408"],
				"id": "43a8d"
			},
			{
				"level": 1,
				"id": "05a13",
				"itemsIds": ["173", "553", "588", "1539"],
				"title": "México"
			},
			{
				"title": "Monumentos",
				"level": 2,
				"id": "8be52",
				"itemsIds": ["127", "405", "814", "934"]
			},
			{
				"itemsIds": ["2032", "1501", "1484", "1592"],
				"title": "Internet",
				"id": "7654f",
				"level": 3
			}
		]
	},
	"17": {
		"id": "2025-03-17",
		"type": "quartetos",
		"number": 17,
		"difficulty": 2,
		"grid": [
			"71",
			"1671",
			"44",
			"842",
			"2274",
			"613",
			"667",
			"1055",
			"1751",
			"330",
			"1",
			"151",
			"1094",
			"2092",
			"757",
			"88"
		],
		"setId": "97e40;;08dba;;a1f4d;;ebba0",
		"sets": [
			{
				"title": "Contém camadas",
				"level": 0,
				"itemsIds": ["71", "1055", "1751", "2274"],
				"id": "a1f4d"
			},
			{
				"title": "Animais perigosos",
				"level": 1,
				"itemsIds": ["88", "151", "667", "757"],
				"id": "08dba"
			},
			{
				"level": 2,
				"title": "Ajuda a andar",
				"id": "97e40",
				"itemsIds": ["330", "613", "1671", "2092"]
			},
			{
				"itemsIds": ["842", "44", "1094", "1"],
				"id": "ebba0",
				"title": "Academia",
				"level": 3
			}
		]
	},
	"18": {
		"id": "2025-03-18",
		"type": "quartetos",
		"number": 18,
		"difficulty": 1,
		"grid": [
			"532",
			"484",
			"1",
			"726",
			"744",
			"72",
			"477",
			"1300",
			"1320",
			"622",
			"308",
			"2103",
			"442",
			"1376",
			"707",
			"2284"
		],
		"setId": "b31e9;;1097d;;03cdc;;c10eb",
		"sets": [
			{
				"level": 0,
				"title": "Identificação",
				"id": "b31e9",
				"itemsIds": ["477", "726", "1376", "2103"]
			},
			{
				"title": "Plantas",
				"level": 1,
				"id": "1097d",
				"itemsIds": ["72", "308", "532", "622"]
			},
			{
				"level": 2,
				"title": "Relaxar",
				"itemsIds": ["1", "442", "707", "744"],
				"id": "03cdc"
			},
			{
				"itemsIds": ["484", "1320", "2284", "1300"],
				"level": 3,
				"id": "c10eb",
				"title": "Rosa"
			}
		]
	},
	"19": {
		"id": "2025-03-19",
		"type": "quartetos",
		"number": 19,
		"difficulty": 2,
		"grid": [
			"2132",
			"1402",
			"303",
			"76",
			"646",
			"819",
			"147",
			"372",
			"708",
			"751",
			"729",
			"118",
			"74",
			"686",
			"239",
			"22"
		],
		"setId": "73c5f;;e27b7;;17e76;;a53d1",
		"sets": [
			{
				"level": 0,
				"title": "Chaves",
				"id": "17e76",
				"itemsIds": ["74", "646", "686", "729"]
			},
			{
				"title": "Já",
				"itemsIds": ["147", "303", "708", "819"],
				"id": "e27b7",
				"level": 1
			},
			{
				"itemsIds": ["76", "118", "372", "1402"],
				"id": "73c5f",
				"title": "Casamento",
				"level": 2
			},
			{
				"title": "Seduzindo",
				"id": "a53d1",
				"itemsIds": ["2132", "239", "22", "751"],
				"level": 3
			}
		]
	},
	"20": {
		"id": "2025-03-20",
		"type": "quartetos",
		"number": 20,
		"difficulty": 1,
		"grid": [
			"1533",
			"213",
			"407",
			"245",
			"2438",
			"1380",
			"435",
			"408",
			"941",
			"417",
			"104",
			"540",
			"839",
			"215",
			"911",
			"891"
		],
		"setId": "8b5b3;;a5bb2;;c4549;;44893",
		"sets": [
			{
				"id": "8b5b3",
				"level": 0,
				"itemsIds": ["245", "407", "408", "839"],
				"title": "Colocar dentro"
			},
			{
				"id": "c4549",
				"itemsIds": ["104", "435", "891", "911"],
				"level": 1,
				"title": "Senta lá, Cláudia!"
			},
			{
				"id": "44893",
				"itemsIds": ["2438", "941", "1380", "1533"],
				"level": 2,
				"title": "Nozes e castanhas"
			},
			{
				"id": "a5bb2",
				"itemsIds": ["213", "215", "417", "540"],
				"title": "No pé",
				"level": 3
			}
		]
	},
	"21": {
		"id": "2025-03-21",
		"type": "quartetos",
		"number": 21,
		"difficulty": 2,
		"grid": [
			"413",
			"112",
			"1024",
			"261",
			"107",
			"440",
			"397",
			"32",
			"1137",
			"10",
			"310",
			"478",
			"105",
			"1464",
			"798",
			"202"
		],
		"setId": "64444;;0916a;;19e3a;;197b1",
		"sets": [
			{
				"title": "Coisas que você entra",
				"itemsIds": ["10", "105", "107", "440"],
				"level": 0,
				"id": "64444"
			},
			{
				"level": 1,
				"itemsIds": ["202", "310", "478", "1024"],
				"title": "Costureira",
				"id": "0916a"
			},
			{
				"level": 2,
				"itemsIds": ["112", "397", "1137", "1464"],
				"id": "19e3a",
				"title": "Pagamento"
			},
			{
				"id": "197b1",
				"level": 3,
				"title": "Bandeiras",
				"itemsIds": ["798", "32", "261", "413"]
			}
		]
	},
	"22": {
		"id": "2025-03-22",
		"type": "quartetos",
		"number": 22,
		"difficulty": 2,
		"grid": [
			"226",
			"496",
			"316",
			"2444",
			"2295",
			"324",
			"2701",
			"280",
			"463",
			"493",
			"2294",
			"2159",
			"626",
			"452",
			"79",
			"1565"
		],
		"setId": "3df11;;19d2f;;4119a;;9ddad",
		"sets": [
			{
				"level": 0,
				"title": "Dois lados",
				"itemsIds": ["280", "463", "493", "496"],
				"id": "3df11"
			},
			{
				"id": "19d2f",
				"title": "Gelado",
				"itemsIds": ["79", "226", "452", "1565"],
				"level": 1
			},
			{
				"title": "Proteção para a cabeça",
				"id": "4119a",
				"itemsIds": ["316", "324", "626", "2701"],
				"level": 2
			},
			{
				"itemsIds": ["2295", "2294", "2159", "2444"],
				"id": "9ddad",
				"title": "Prisão",
				"level": 3
			}
		]
	},
	"23": {
		"id": "2025-03-23",
		"type": "quartetos",
		"number": 23,
		"difficulty": 2,
		"grid": [
			"1471",
			"217",
			"1060",
			"139",
			"189",
			"138",
			"339",
			"422",
			"1057",
			"259",
			"109",
			"1056",
			"520",
			"813",
			"656",
			"1053"
		],
		"setId": "dbee2;;ac2af;;dd461;;9a184",
		"sets": [
			{
				"level": 0,
				"title": "Esfera",
				"itemsIds": ["138", "139", "189", "813"],
				"id": "dd461"
			},
			{
				"itemsIds": ["109", "339", "422", "520"],
				"id": "dbee2",
				"title": "Acessórios da moda",
				"level": 1
			},
			{
				"id": "ac2af",
				"title": "Utensílios esportivos",
				"level": 2,
				"itemsIds": ["217", "259", "656", "1471"]
			},
			{
				"itemsIds": ["1056", "1060", "1053", "1057"],
				"level": 3,
				"title": "Espaço",
				"id": "9a184"
			}
		]
	},
	"24": {
		"id": "2025-03-24",
		"type": "quartetos",
		"number": 24,
		"difficulty": 3,
		"grid": [
			"327",
			"1930",
			"300",
			"1386",
			"605",
			"245",
			"1929",
			"440",
			"161",
			"177",
			"15",
			"204",
			"2211",
			"137",
			"429",
			"254"
		],
		"setId": "23c11;;8f04e;;72018;;788a9",
		"sets": [
			{
				"id": "23c11",
				"title": "Pares",
				"level": 0,
				"itemsIds": ["15", "204", "254", "327"]
			},
			{
				"id": "8f04e",
				"title": "Rima com \"vagem\" (bagagem, carruagem, maquiagem, chantagem)",
				"itemsIds": ["245", "440", "1386", "2211"],
				"level": 1
			},
			{
				"itemsIds": ["137", "161", "177", "605"],
				"id": "72018",
				"title": "Transmissão",
				"level": 2
			},
			{
				"itemsIds": ["1930", "429", "1929", "300"],
				"id": "788a9",
				"title": "Voo",
				"level": 3
			}
		]
	},
	"25": {
		"id": "2025-03-25",
		"type": "quartetos",
		"number": 25,
		"difficulty": 2,
		"grid": [
			"436",
			"2162",
			"1410",
			"54",
			"588",
			"390",
			"398",
			"1409",
			"125",
			"2022",
			"127",
			"393",
			"291",
			"363",
			"521",
			"1411"
		],
		"setId": "e4c0e;;f3b51;;e0888;;cc21f",
		"sets": [
			{
				"itemsIds": ["127", "390", "521", "588"],
				"level": 0,
				"id": "f3b51",
				"title": "Triângulo amarelo"
			},
			{
				"itemsIds": ["125", "363", "436", "2022"],
				"title": "Ingredientes para pizza",
				"level": 1,
				"id": "e4c0e"
			},
			{
				"id": "cc21f",
				"title": "Danças",
				"itemsIds": ["1409", "2162", "1410", "1411"],
				"level": 2
			},
			{
				"level": 3,
				"itemsIds": ["54", "291", "393", "398"],
				"title": "Vamos cozinhar!",
				"id": "e0888"
			}
		]
	},
	"26": {
		"id": "2025-03-26",
		"type": "quartetos",
		"number": 26,
		"difficulty": 2,
		"grid": [
			"832",
			"2369",
			"1895",
			"56",
			"103",
			"1450",
			"202",
			"1593",
			"790",
			"511",
			"22",
			"123",
			"1520",
			"154",
			"211",
			"76"
		],
		"setId": "bfbfb;;6c2f3;;3c718;;cb7a8",
		"sets": [
			{
				"title": "Bolinha amarelo",
				"id": "6c2f3",
				"itemsIds": ["56", "103", "790", "832"],
				"level": 0
			},
			{
				"level": 1,
				"id": "bfbfb",
				"title": "Plantação",
				"itemsIds": ["211", "511", "1520", "1593"]
			},
			{
				"id": "3c718",
				"level": 2,
				"itemsIds": ["22", "76", "123", "202"],
				"title": "Roupa de mulher"
			},
			{
				"id": "cb7a8",
				"title": "Preto",
				"itemsIds": ["2369", "154", "1450", "1895"],
				"level": 3
			}
		]
	},
	"27": {
		"id": "2025-03-27",
		"type": "quartetos",
		"number": 27,
		"difficulty": 2,
		"grid": [
			"475",
			"339",
			"681",
			"83",
			"264",
			"154",
			"38",
			"520",
			"695",
			"6",
			"207",
			"107",
			"2039",
			"2029",
			"801",
			"152"
		],
		"setId": "9d92a;;978dd;;51036;;7761d",
		"sets": [
			{
				"level": 0,
				"id": "51036",
				"itemsIds": ["107", "152", "154", "475"],
				"title": "Portas"
			},
			{
				"title": "Mensagem",
				"level": 1,
				"id": "9d92a",
				"itemsIds": ["6", "83", "681", "695"]
			},
			{
				"id": "978dd",
				"title": "No pescoço",
				"level": 2,
				"itemsIds": ["207", "264", "339", "520"]
			},
			{
				"title": "Tinta",
				"level": 3,
				"id": "7761d",
				"itemsIds": ["2039", "38", "801", "2029"]
			}
		]
	},
	"28": {
		"id": "2025-03-28",
		"type": "quartetos",
		"number": 28,
		"difficulty": 2,
		"grid": [
			"1737",
			"273",
			"739",
			"2027",
			"186",
			"1940",
			"444",
			"2827",
			"1974",
			"596",
			"1106",
			"588",
			"1192",
			"2347",
			"826",
			"1318"
		],
		"setId": "0c1e8;;f7fc6;;ad1e5;;9e782",
		"sets": [
			{
				"title": "Sol",
				"level": 0,
				"itemsIds": ["588", "596", "739", "826"],
				"id": "0c1e8"
			},
			{
				"level": 1,
				"itemsIds": ["1737", "1940", "1974", "2827"],
				"title": "Crianças",
				"id": "f7fc6"
			},
			{
				"id": "ad1e5",
				"title": "Vamos caçar",
				"itemsIds": ["186", "273", "444", "1192"],
				"level": 2
			},
			{
				"itemsIds": ["2347", "1106", "2027", "1318"],
				"id": "9e782",
				"level": 3,
				"title": "Fantasia"
			}
		]
	},
	"29": {
		"id": "2025-03-29",
		"type": "quartetos",
		"number": 29,
		"difficulty": 2,
		"grid": [
			"386",
			"352",
			"434",
			"105",
			"230",
			"1532",
			"839",
			"117",
			"900",
			"1487",
			"719",
			"351",
			"873",
			"815",
			"861",
			"448"
		],
		"setId": "c1a6a;;08636;;c3099;;15b25",
		"sets": [
			{
				"title": "Morri",
				"level": 0,
				"itemsIds": ["105", "351", "352", "434"],
				"id": "c1a6a"
			},
			{
				"itemsIds": ["117", "230", "386", "1532"],
				"id": "08636",
				"title": "Pássaros",
				"level": 1
			},
			{
				"id": "c3099",
				"itemsIds": ["719", "815", "839", "873"],
				"title": "Guarde aqui!",
				"level": 2
			},
			{
				"itemsIds": ["900", "448", "1487", "861"],
				"title": "Asiático",
				"level": 3,
				"id": "15b25"
			}
		]
	},
	"30": {
		"id": "2025-03-30",
		"type": "quartetos",
		"number": 30,
		"difficulty": 2,
		"grid": [
			"353",
			"280",
			"416",
			"194",
			"395",
			"294",
			"918",
			"277",
			"378",
			"246",
			"388",
			"812",
			"606",
			"632",
			"31",
			"154"
		],
		"setId": "76f9a;;de5a8;;8bd62;;528cd",
		"sets": [
			{
				"title": "Coisas que precisam de ar",
				"itemsIds": ["194", "416", "632", "812"],
				"level": 0,
				"id": "8bd62"
			},
			{
				"title": "Eletrodomésticos",
				"id": "76f9a",
				"level": 1,
				"itemsIds": ["154", "395", "606", "918"]
			},
			{
				"level": 2,
				"id": "de5a8",
				"itemsIds": ["277", "280", "353", "388"],
				"title": "No parquinho"
			},
			{
				"id": "528cd",
				"itemsIds": ["31", "294", "246", "378"],
				"title": "Feriados",
				"level": 3
			}
		]
	},
	"31": {
		"id": "2025-03-31",
		"type": "quartetos",
		"number": 31,
		"difficulty": 2,
		"grid": [
			"2357",
			"2243",
			"888",
			"1982",
			"312",
			"302",
			"34",
			"1300",
			"35",
			"249",
			"1498",
			"5",
			"36",
			"299",
			"320",
			"657"
		],
		"setId": "f35bf;;b7dbc;;29cf5;;fb04b",
		"sets": [
			{
				"level": 0,
				"title": "Cheiro forte",
				"id": "f35bf",
				"itemsIds": ["5", "249", "302", "657"]
			},
			{
				"itemsIds": ["34", "35", "36", "312"],
				"title": "Calavos",
				"level": 1,
				"id": "b7dbc"
			},
			{
				"id": "29cf5",
				"level": 2,
				"itemsIds": ["299", "320", "888", "1300"],
				"title": "Material Escolar"
			},
			{
				"title": "Local",
				"id": "fb04b",
				"itemsIds": ["2243", "1498", "1982", "2357"],
				"level": 3
			}
		]
	},
	"32": {
		"id": "2025-04-01",
		"type": "quartetos",
		"number": 32,
		"difficulty": 2,
		"grid": [
			"405",
			"79",
			"285",
			"1646",
			"1611",
			"174",
			"814",
			"633",
			"109",
			"1595",
			"745",
			"1798",
			"544",
			"247",
			"62",
			"422"
		],
		"setId": "4987a;;55c86;;9e6f5;;21592",
		"sets": [
			{
				"itemsIds": ["62", "109", "285", "422"],
				"title": "Coisas que seguram coisas",
				"level": 0,
				"id": "55c86"
			},
			{
				"title": "França",
				"level": 1,
				"itemsIds": ["405", "633", "814", "1595"],
				"id": "9e6f5"
			},
			{
				"id": "4987a",
				"level": 2,
				"itemsIds": ["174", "247", "544", "745"],
				"title": "Hospital"
			},
			{
				"itemsIds": ["79", "1611", "1798", "1646"],
				"title": "Sobremesas",
				"id": "21592",
				"level": 3
			}
		]
	},
	"33": {
		"id": "2025-04-02",
		"type": "quartetos",
		"number": 33,
		"difficulty": 2,
		"grid": [
			"1897",
			"1465",
			"87",
			"103",
			"530",
			"368",
			"754",
			"531",
			"203",
			"1535",
			"693",
			"4",
			"39",
			"720",
			"625",
			"1904"
		],
		"setId": "1e8c8;;83a56;;f851f;;25ff6",
		"sets": [
			{
				"itemsIds": ["39", "87", "720", "1465"],
				"id": "83a56",
				"title": "Músicas do BTS (butter, dna, fire, butterfly)",
				"level": 0
			},
			{
				"id": "1e8c8",
				"level": 1,
				"title": "Guerra",
				"itemsIds": ["4", "103", "368", "531"]
			},
			{
				"level": 2,
				"itemsIds": ["203", "530", "625", "1897"],
				"title": "Membros coporais",
				"id": "f851f"
			},
			{
				"id": "25ff6",
				"title": "Vegetais",
				"level": 3,
				"itemsIds": ["754", "693", "1904", "1535"]
			}
		]
	},
	"34": {
		"id": "2025-04-03",
		"type": "quartetos",
		"number": 34,
		"difficulty": 1,
		"grid": [
			"26",
			"1407",
			"226",
			"69",
			"224",
			"1124",
			"83",
			"79",
			"282",
			"354",
			"27",
			"1465",
			"1390",
			"2436",
			"1452",
			"1546"
		],
		"setId": "8c8cc;;1126f;;9431b;;d47b5",
		"sets": [
			{
				"id": "8c8cc",
				"level": 0,
				"title": "Derretendo...",
				"itemsIds": ["79", "226", "1465", "2436"]
			},
			{
				"title": "Jogos e Atividades",
				"id": "9431b",
				"level": 1,
				"itemsIds": ["1390", "1407", "1452", "1546"]
			},
			{
				"level": 2,
				"itemsIds": ["1124", "83", "27", "26"],
				"id": "d47b5",
				"title": "Adolescentes"
			},
			{
				"title": "Vamos salvar vidas",
				"level": 3,
				"itemsIds": ["69", "224", "282", "354"],
				"id": "1126f"
			}
		]
	},
	"35": {
		"id": "2025-04-04",
		"type": "quartetos",
		"number": 35,
		"difficulty": 2,
		"grid": [
			"5",
			"2279",
			"1248",
			"704",
			"1170",
			"48",
			"63",
			"804",
			"1962",
			"687",
			"148",
			"217",
			"994",
			"126",
			"376",
			"180"
		],
		"setId": "5e1f7;;9d202;;a4f2d;;b473c",
		"sets": [
			{
				"id": "a4f2d",
				"level": 0,
				"title": "Ofendendo um homem",
				"itemsIds": ["5", "148", "1248", "2279"]
			},
			{
				"level": 1,
				"title": "Redondo com buraco no meio",
				"id": "5e1f7",
				"itemsIds": ["48", "180", "804", "1170"]
			},
			{
				"itemsIds": ["217", "376", "687", "704"],
				"id": "9d202",
				"title": "Símbolos fálicos",
				"level": 2
			},
			{
				"level": 3,
				"title": "Homens",
				"id": "b473c",
				"itemsIds": ["63", "1962", "126", "994"]
			}
		]
	},
	"36": {
		"id": "2025-04-05",
		"type": "quartetos",
		"number": 36,
		"difficulty": 2,
		"grid": [
			"2052",
			"1605",
			"8",
			"2789",
			"2056",
			"318",
			"2521",
			"2051",
			"2773",
			"789",
			"1497",
			"2900",
			"143",
			"2058",
			"764",
			"740"
		],
		"setId": "c9bc4;;0b55e;;b7676;;58c9e",
		"sets": [
			{
				"id": "b7676",
				"level": 0,
				"itemsIds": ["740", "2773", "2789", "2900"],
				"title": "Tipos de Parques"
			},
			{
				"itemsIds": ["8", "318", "764", "2521"],
				"level": 1,
				"id": "c9bc4",
				"title": "Aniversário de Criança"
			},
			{
				"level": 2,
				"itemsIds": ["143", "789", "1497", "1605"],
				"title": "Notas musicais",
				"id": "0b55e"
			},
			{
				"level": 3,
				"id": "58c9e",
				"title": "Cores",
				"itemsIds": ["2052", "2056", "2051", "2058"]
			}
		]
	},
	"37": {
		"id": "2025-04-06",
		"type": "quartetos",
		"number": 37,
		"difficulty": 2,
		"grid": [
			"2304",
			"482",
			"354",
			"1827",
			"219",
			"1684",
			"162",
			"460",
			"91",
			"489",
			"813",
			"148",
			"1288",
			"509",
			"742",
			"2"
		],
		"setId": "52b69;;18e2e;;a6378;;75187",
		"sets": [
			{
				"id": "52b69",
				"title": "Cabe muita gente",
				"itemsIds": ["219", "482", "489", "509"],
				"level": 0
			},
			{
				"itemsIds": ["91", "354", "460", "1288"],
				"id": "18e2e",
				"title": "Alto mar",
				"level": 1
			},
			{
				"itemsIds": ["148", "162", "742", "1827"],
				"title": "Bichos de estimação",
				"level": 2,
				"id": "a6378"
			},
			{
				"title": "Praia",
				"level": 3,
				"itemsIds": ["813", "2304", "1684", "2"],
				"id": "75187"
			}
		]
	},
	"38": {
		"id": "2025-04-07",
		"type": "quartetos",
		"number": 38,
		"difficulty": 2,
		"grid": [
			"46",
			"2226",
			"2222",
			"51",
			"437",
			"392",
			"438",
			"286",
			"2279",
			"1125",
			"83",
			"710",
			"885",
			"130",
			"550",
			"1957"
		],
		"setId": "246b0;;3c76f;;a90a5;;093f3",
		"sets": [
			{
				"level": 0,
				"itemsIds": ["83", "130", "392", "1125"],
				"id": "3c76f",
				"title": "Tem senha"
			},
			{
				"title": "Rodas",
				"level": 1,
				"itemsIds": ["437", "438", "550", "710"],
				"id": "a90a5"
			},
			{
				"level": 2,
				"title": "Bovinos",
				"itemsIds": ["46", "1957", "2226", "2279"],
				"id": "246b0"
			},
			{
				"level": 3,
				"id": "093f3",
				"title": "Parque de diversões",
				"itemsIds": ["2222", "885", "51", "286"]
			}
		]
	},
	"39": {
		"id": "2025-04-08",
		"type": "quartetos",
		"number": 39,
		"difficulty": 1,
		"grid": [
			"1540",
			"747",
			"882",
			"774",
			"1186",
			"1347",
			"257",
			"560",
			"632",
			"402",
			"440",
			"15",
			"2814",
			"1385",
			"530",
			"1149"
		],
		"setId": "336ec;;a74ba;;ab350;;f28b7",
		"sets": [
			{
				"level": 0,
				"id": "a74ba",
				"title": "Contos de fadas",
				"itemsIds": ["440", "560", "1385", "1540"]
			},
			{
				"itemsIds": ["257", "530", "747", "774"],
				"title": "Mãos",
				"id": "ab350",
				"level": 1
			},
			{
				"level": 2,
				"itemsIds": ["1186", "882", "1149", "15"],
				"title": "Esportes",
				"id": "f28b7"
			},
			{
				"itemsIds": ["402", "632", "1347", "2814"],
				"title": "Parte Interna do Corpo",
				"id": "336ec",
				"level": 3
			}
		]
	},
	"40": {
		"id": "2025-04-09",
		"type": "quartetos",
		"number": 40,
		"difficulty": 2,
		"grid": [
			"530",
			"574",
			"1286",
			"272",
			"298",
			"98",
			"501",
			"320",
			"330",
			"399",
			"208",
			"74",
			"1913",
			"1076",
			"2211",
			"1786"
		],
		"setId": "c0797;;c9801;;bb662;;6592a",
		"sets": [
			{
				"itemsIds": ["298", "320", "399", "530"],
				"id": "c9801",
				"level": 0,
				"title": "Coisas usadas para medir"
			},
			{
				"level": 1,
				"title": "Madeira",
				"id": "c0797",
				"itemsIds": ["74", "98", "574", "1913"]
			},
			{
				"level": 2,
				"id": "bb662",
				"itemsIds": ["208", "272", "330", "501"],
				"title": "Machuquei"
			},
			{
				"id": "6592a",
				"level": 3,
				"itemsIds": ["2211", "1786", "1076", "1286"],
				"title": "Mal"
			}
		]
	},
	"41": {
		"id": "2025-04-10",
		"type": "quartetos",
		"number": 41,
		"difficulty": 1,
		"grid": [
			"567",
			"2144",
			"143",
			"304",
			"316",
			"8",
			"1609",
			"593",
			"2142",
			"67",
			"2206",
			"466",
			"83",
			"661",
			"792",
			"1600"
		],
		"setId": "b7630;;9a47a;;977c1;;674b6",
		"sets": [
			{
				"title": "Explosão",
				"itemsIds": ["67", "304", "593", "2206"],
				"level": 0,
				"id": "b7630"
			},
			{
				"itemsIds": ["83", "143", "466", "661"],
				"level": 1,
				"id": "9a47a",
				"title": "Fala que eu te escuto"
			},
			{
				"level": 2,
				"itemsIds": ["567", "792", "1600", "1609"],
				"id": "977c1",
				"title": "Comidas redondinhas"
			},
			{
				"itemsIds": ["8", "2142", "2144", "316"],
				"id": "674b6",
				"level": 3,
				"title": "Chapéus"
			}
		]
	},
	"42": {
		"id": "2025-04-11",
		"type": "quartetos",
		"number": 42,
		"difficulty": 2,
		"grid": [
			"2158",
			"35",
			"7",
			"289",
			"356",
			"125",
			"348",
			"906",
			"1296",
			"624",
			"122",
			"278",
			"432",
			"2154",
			"2157",
			"577"
		],
		"setId": "db0a2;;44ccf;;42482;;75d6f",
		"sets": [
			{
				"title": "Difícil de segurar",
				"id": "44ccf",
				"level": 0,
				"itemsIds": ["125", "348", "356", "624"]
			},
			{
				"level": 1,
				"itemsIds": ["35", "122", "278", "432"],
				"id": "db0a2",
				"title": "Moradia"
			},
			{
				"id": "42482",
				"itemsIds": ["7", "289", "577", "906"],
				"level": 2,
				"title": "Caixas"
			},
			{
				"itemsIds": ["1296", "2158", "2154", "2157"],
				"level": 3,
				"id": "75d6f",
				"title": "Pirata"
			}
		]
	},
	"43": {
		"id": "2025-04-12",
		"type": "quartetos",
		"number": 43,
		"difficulty": 2,
		"grid": [
			"1376",
			"916",
			"854",
			"811",
			"859",
			"407",
			"2103",
			"572",
			"16",
			"245",
			"80",
			"231",
			"831",
			"362",
			"294",
			"7"
		],
		"setId": "2cb36;;d9da2;;4dc41;;570be",
		"sets": [
			{
				"level": 0,
				"id": "d9da2",
				"itemsIds": ["294", "854", "859", "916"],
				"title": "Tem estrela"
			},
			{
				"itemsIds": ["16", "80", "362", "572"],
				"title": "No fundo do mar",
				"id": "2cb36",
				"level": 1
			},
			{
				"id": "4dc41",
				"title": "Segura na alça",
				"itemsIds": ["7", "231", "245", "407"],
				"level": 2
			},
			{
				"title": "Identificação",
				"id": "570be",
				"level": 3,
				"itemsIds": ["831", "1376", "2103", "811"]
			}
		]
	},
	"44": {
		"id": "2025-04-13",
		"type": "quartetos",
		"number": 44,
		"difficulty": 2,
		"grid": [
			"2331",
			"312",
			"2360",
			"786",
			"419",
			"1887",
			"667",
			"70",
			"115",
			"1139",
			"2359",
			"1999",
			"155",
			"2000",
			"447",
			"552"
		],
		"setId": "80103;;ac2ec;;96999;;68985",
		"sets": [
			{
				"level": 0,
				"itemsIds": ["312", "786", "1139", "2331"],
				"title": "Feito de couro",
				"id": "ac2ec"
			},
			{
				"id": "96999",
				"level": 1,
				"title": "Aladdin",
				"itemsIds": ["70", "552", "667", "1887"]
			},
			{
				"id": "80103",
				"itemsIds": ["115", "447", "1999", "2000"],
				"title": "Pedras",
				"level": 2
			},
			{
				"itemsIds": ["2360", "155", "2359", "419"],
				"id": "68985",
				"level": 3,
				"title": "Bolas"
			}
		]
	},
	"45": {
		"id": "2025-04-14",
		"type": "quartetos",
		"number": 45,
		"difficulty": 2,
		"grid": [
			"464",
			"1335",
			"448",
			"507",
			"211",
			"643",
			"2525",
			"283",
			"468",
			"20",
			"795",
			"579",
			"415",
			"1697",
			"642",
			"382"
		],
		"setId": "4996f;;1f273;;40ef9;;25ff6",
		"sets": [
			{
				"level": 0,
				"title": "Onde fica o que",
				"itemsIds": ["283", "382", "415", "468"],
				"id": "4996f"
			},
			{
				"itemsIds": ["448", "464", "642", "643"],
				"level": 1,
				"title": "Uso para comer",
				"id": "1f273"
			},
			{
				"level": 2,
				"id": "40ef9",
				"itemsIds": ["20", "507", "579", "1335"],
				"title": "Natal"
			},
			{
				"id": "25ff6",
				"itemsIds": ["2525", "1697", "211", "795"],
				"title": "Vegetais",
				"level": 3
			}
		]
	},
	"46": {
		"id": "2025-04-15",
		"type": "quartetos",
		"number": 46,
		"difficulty": 2,
		"grid": [
			"2512",
			"2638",
			"719",
			"1846",
			"201",
			"463",
			"499",
			"104",
			"1469",
			"98",
			"1527",
			"522",
			"124",
			"2664",
			"588",
			"893"
		],
		"setId": "4ce8f;;5f410;;727a2;;af297",
		"sets": [
			{
				"itemsIds": ["893", "1469", "2638", "2664"],
				"id": "4ce8f",
				"level": 0,
				"title": "Usado em um sequestro"
			},
			{
				"title": "Antigo",
				"itemsIds": ["124", "499", "522", "588"],
				"level": 1,
				"id": "727a2"
			},
			{
				"id": "5f410",
				"level": 2,
				"itemsIds": ["201", "1846", "2512", "1527"],
				"title": "Discurso em inglês do Bolsonaro"
			},
			{
				"title": "Móveis",
				"itemsIds": ["719", "98", "104", "463"],
				"id": "af297",
				"level": 3
			}
		]
	},
	"47": {
		"id": "2025-04-16",
		"type": "quartetos",
		"number": 47,
		"difficulty": 1,
		"grid": [
			"457",
			"909",
			"100",
			"612",
			"619",
			"361",
			"185",
			"119",
			"594",
			"833",
			"859",
			"937",
			"2420",
			"948",
			"2144",
			"1895"
		],
		"setId": "b0775;;a5b1f;;cf988;;cb7a8",
		"sets": [
			{
				"itemsIds": ["361", "859", "937", "948"],
				"title": "Elenco do Bob Esponja",
				"level": 0,
				"id": "b0775"
			},
			{
				"itemsIds": ["119", "619", "833", "909"],
				"title": "Vasilhas",
				"level": 1,
				"id": "cf988"
			},
			{
				"title": "Preto",
				"itemsIds": ["2420", "185", "2144", "1895"],
				"id": "cb7a8",
				"level": 2
			},
			{
				"title": "Cordas",
				"itemsIds": ["100", "457", "594", "612"],
				"id": "a5b1f",
				"level": 3
			}
		]
	},
	"48": {
		"id": "2025-04-17",
		"type": "quartetos",
		"number": 48,
		"difficulty": 2,
		"grid": [
			"637",
			"100",
			"82",
			"714",
			"2284",
			"751",
			"1360",
			"459",
			"405",
			"97",
			"1402",
			"441",
			"2603",
			"161",
			"641",
			"2201"
		],
		"setId": "f6d3d;;28ca6;;05bf0;;1d15b",
		"sets": [
			{
				"itemsIds": ["441", "637", "714", "751"],
				"id": "f6d3d",
				"level": 0,
				"title": "Poste"
			},
			{
				"id": "28ca6",
				"title": "Alto",
				"itemsIds": ["97", "161", "405", "459"],
				"level": 1
			},
			{
				"id": "05bf0",
				"itemsIds": ["100", "641", "1360", "2201"],
				"level": 2,
				"title": "Vaqueiro"
			},
			{
				"title": "Casamento",
				"id": "1d15b",
				"level": 3,
				"itemsIds": ["2603", "2284", "1402", "82"]
			}
		]
	},
	"49": {
		"id": "2025-04-18",
		"type": "quartetos",
		"number": 49,
		"difficulty": 2,
		"grid": [
			"1397",
			"275",
			"622",
			"526",
			"945",
			"728",
			"131",
			"1114",
			"1400",
			"785",
			"1039",
			"335",
			"651",
			"83",
			"135",
			"661"
		],
		"setId": "321f3;;b8624;;f3b2b;;a158a",
		"sets": [
			{
				"level": 0,
				"id": "321f3",
				"itemsIds": ["275", "622", "785", "945"],
				"title": "Lugares para fazer cocô"
			},
			{
				"level": 1,
				"title": "Insetos",
				"itemsIds": ["135", "526", "651", "728"],
				"id": "b8624"
			},
			{
				"itemsIds": ["83", "131", "335", "661"],
				"level": 2,
				"title": "Quantas horas são?",
				"id": "f3b2b"
			},
			{
				"itemsIds": ["1397", "1114", "1039", "1400"],
				"id": "a158a",
				"title": "Mão",
				"level": 3
			}
		]
	},
	"50": {
		"id": "2025-04-19",
		"type": "quartetos",
		"number": 50,
		"difficulty": 2,
		"grid": [
			"545",
			"254",
			"389",
			"183",
			"1367",
			"1054",
			"369",
			"305",
			"430",
			"1058",
			"748",
			"634",
			"749",
			"1285",
			"2771",
			"613"
		],
		"setId": "c2e4d;;33265;;02a95;;9a184",
		"sets": [
			{
				"title": "Rima com \"ala\" (bala, bengala, coala, sala)",
				"itemsIds": ["545", "613", "1285", "2771"],
				"id": "02a95",
				"level": 0
			},
			{
				"id": "c2e4d",
				"level": 1,
				"itemsIds": ["183", "634", "748", "749"],
				"title": "Vencedor"
			},
			{
				"title": "Ficar bonita",
				"itemsIds": ["254", "305", "369", "430"],
				"id": "33265",
				"level": 2
			},
			{
				"title": "Espaço",
				"id": "9a184",
				"level": 3,
				"itemsIds": ["1058", "1054", "1367", "389"]
			}
		]
	}
}
