{
	"dcp-1-en": {
		"id": "dcp-1-en",
		"text": "acquired"
	},
	"dcp-2-en": {
		"id": "dcp-2-en",
		"text": "adaptable"
	},
	"dcp-3-en": {
		"id": "dcp-3-en",
		"text": "advertised"
	},
	"dcp-4-en": {
		"id": "dcp-4-en",
		"text": "aggressive"
	},
	"dcp-5-en": {
		"id": "dcp-5-en",
		"text": "annoying"
	},
	"dcp-6-en": {
		"id": "dcp-6-en",
		"text": "aromatic"
	},
	"dcp-7-en": {
		"id": "dcp-7-en",
		"text": "asian"
	},
	"dcp-8-en": {
		"id": "dcp-8-en",
		"text": "bad"
	},
	"dcp-9-en": {
		"id": "dcp-9-en",
		"text": "beautiful"
	},
	"dcp-10-en": {
		"id": "dcp-10-en",
		"text": "bitter"
	},
	"dcp-11-en": {
		"id": "dcp-11-en",
		"text": "black"
	},
	"dcp-12-en": {
		"id": "dcp-12-en",
		"text": "blue"
	},
	"dcp-13-en": {
		"id": "dcp-13-en",
		"text": "blunt"
	},
	"dcp-14-en": {
		"id": "dcp-14-en",
		"text": "bouncy"
	},
	"dcp-15-en": {
		"id": "dcp-15-en",
		"text": "brainy"
	},
	"dcp-16-en": {
		"id": "dcp-16-en",
		"text": "breakable"
	},
	"dcp-17-en": {
		"id": "dcp-17-en",
		"text": "bright"
	},
	"dcp-18-en": {
		"id": "dcp-18-en",
		"text": "bulletproof"
	},
	"dcp-19-en": {
		"id": "dcp-19-en",
		"text": "calm"
	},
	"dcp-20-en": {
		"id": "dcp-20-en",
		"text": "casual"
	},
	"dcp-21-en": {
		"id": "dcp-21-en",
		"text": "celestial"
	},
	"dcp-22-en": {
		"id": "dcp-22-en",
		"text": "chemical"
	},
	"dcp-23-en": {
		"id": "dcp-23-en",
		"text": "classic"
	},
	"dcp-24-en": {
		"id": "dcp-24-en",
		"text": "commercial"
	},
	"dcp-25-en": {
		"id": "dcp-25-en",
		"text": "contagious"
	},
	"dcp-26-en": {
		"id": "dcp-26-en",
		"text": "cool"
	},
	"dcp-27-en": {
		"id": "dcp-27-en",
		"text": "cosmic"
	},
	"dcp-28-en": {
		"id": "dcp-28-en",
		"text": "cowardly"
	},
	"dcp-29-en": {
		"id": "dcp-29-en",
		"text": "cozy"
	},
	"dcp-30-en": {
		"id": "dcp-30-en",
		"text": "craft"
	},
	"dcp-31-en": {
		"id": "dcp-31-en",
		"text": "creative"
	},
	"dcp-32-en": {
		"id": "dcp-32-en",
		"text": "cringe"
	},
	"dcp-33-en": {
		"id": "dcp-33-en",
		"text": "cute"
	},
	"dcp-34-en": {
		"id": "dcp-34-en",
		"text": "decorative"
	},
	"dcp-35-en": {
		"id": "dcp-35-en",
		"text": "deep"
	},
	"dcp-36-en": {
		"id": "dcp-36-en",
		"text": "delicious"
	},
	"dcp-37-en": {
		"id": "dcp-37-en",
		"text": "delightful"
	},
	"dcp-38-en": {
		"id": "dcp-38-en",
		"text": "dense"
	},
	"dcp-39-en": {
		"id": "dcp-39-en",
		"text": "digital"
	},
	"dcp-40-en": {
		"id": "dcp-40-en",
		"text": "direct"
	},
	"dcp-41-en": {
		"id": "dcp-41-en",
		"text": "dirty"
	},
	"dcp-42-en": {
		"id": "dcp-42-en",
		"text": "disappointing"
	},
	"dcp-43-en": {
		"id": "dcp-43-en",
		"text": "disposable"
	},
	"dcp-44-en": {
		"id": "dcp-44-en",
		"text": "divine"
	},
	"dcp-45-en": {
		"id": "dcp-45-en",
		"text": "dry"
	},
	"dcp-46-en": {
		"id": "dcp-46-en",
		"text": "dull"
	},
	"dcp-47-en": {
		"id": "dcp-47-en",
		"text": "dusty"
	},
	"dcp-48-en": {
		"id": "dcp-48-en",
		"text": "eastern"
	},
	"dcp-49-en": {
		"id": "dcp-49-en",
		"text": "economic"
	},
	"dcp-50-en": {
		"id": "dcp-50-en",
		"text": "edible"
	},
	"dcp-51-en": {
		"id": "dcp-51-en",
		"text": "educational"
	},
	"dcp-52-en": {
		"id": "dcp-52-en",
		"text": "elastic"
	},
	"dcp-53-en": {
		"id": "dcp-53-en",
		"text": "emotional"
	},
	"dcp-54-en": {
		"id": "dcp-54-en",
		"text": "energetic"
	},
	"dcp-55-en": {
		"id": "dcp-55-en",
		"text": "environmental"
	},
	"dcp-56-en": {
		"id": "dcp-56-en",
		"text": "ethical"
	},
	"dcp-57-en": {
		"id": "dcp-57-en",
		"text": "exotic"
	},
	"dcp-58-en": {
		"id": "dcp-58-en",
		"text": "expensive"
	},
	"dcp-59-en": {
		"id": "dcp-59-en",
		"text": "external"
	},
	"dcp-60-en": {
		"id": "dcp-60-en",
		"text": "fake"
	},
	"dcp-61-en": {
		"id": "dcp-61-en",
		"text": "fashionable"
	},
	"dcp-62-en": {
		"id": "dcp-62-en",
		"text": "fat"
	},
	"dcp-63-en": {
		"id": "dcp-63-en",
		"text": "feminine"
	},
	"dcp-64-en": {
		"id": "dcp-64-en",
		"text": "fingerless"
	},
	"dcp-65-en": {
		"id": "dcp-65-en",
		"text": "fixable"
	},
	"dcp-66-en": {
		"id": "dcp-66-en",
		"text": "flexible"
	},
	"dcp-67-en": {
		"id": "dcp-67-en",
		"text": "fluid"
	},
	"dcp-68-en": {
		"id": "dcp-68-en",
		"text": "flying"
	},
	"dcp-69-en": {
		"id": "dcp-69-en",
		"text": "forbidden"
	},
	"dcp-70-en": {
		"id": "dcp-70-en",
		"text": "foreign"
	},
	"dcp-71-en": {
		"id": "dcp-71-en",
		"text": "formal"
	},
	"dcp-72-en": {
		"id": "dcp-72-en",
		"text": "foul"
	},
	"dcp-73-en": {
		"id": "dcp-73-en",
		"text": "fragile"
	},
	"dcp-74-en": {
		"id": "dcp-74-en",
		"text": "fragrant"
	},
	"dcp-75-en": {
		"id": "dcp-75-en",
		"text": "funny"
	},
	"dcp-76-en": {
		"id": "dcp-76-en",
		"text": "furry"
	},
	"dcp-77-en": {
		"id": "dcp-77-en",
		"text": "good"
	},
	"dcp-78-en": {
		"id": "dcp-78-en",
		"text": "green"
	},
	"dcp-79-en": {
		"id": "dcp-79-en",
		"text": "guilty"
	},
	"dcp-80-en": {
		"id": "dcp-80-en",
		"text": "hanging"
	},
	"dcp-81-en": {
		"id": "dcp-81-en",
		"text": "harsh"
	},
	"dcp-82-en": {
		"id": "dcp-82-en",
		"text": "haunted"
	},
	"dcp-83-en": {
		"id": "dcp-83-en",
		"text": "heartbreaking"
	},
	"dcp-84-en": {
		"id": "dcp-84-en",
		"text": "heavy"
	},
	"dcp-85-en": {
		"id": "dcp-85-en",
		"text": "helpful"
	},
	"dcp-86-en": {
		"id": "dcp-86-en",
		"text": "herbal"
	},
	"dcp-87-en": {
		"id": "dcp-87-en",
		"text": "hollow"
	},
	"dcp-88-en": {
		"id": "dcp-88-en",
		"text": "homogenous"
	},
	"dcp-89-en": {
		"id": "dcp-89-en",
		"text": "honorable"
	},
	"dcp-90-en": {
		"id": "dcp-90-en",
		"text": "hot"
	},
	"dcp-91-en": {
		"id": "dcp-91-en",
		"text": "independent"
	},
	"dcp-92-en": {
		"id": "dcp-92-en",
		"text": "industrial"
	},
	"dcp-93-en": {
		"id": "dcp-93-en",
		"text": "inevitable"
	},
	"dcp-94-en": {
		"id": "dcp-94-en",
		"text": "inherited"
	},
	"dcp-95-en": {
		"id": "dcp-95-en",
		"text": "innocent"
	},
	"dcp-96-en": {
		"id": "dcp-96-en",
		"text": "intellectual"
	},
	"dcp-97-en": {
		"id": "dcp-97-en",
		"text": "interesting"
	},
	"dcp-98-en": {
		"id": "dcp-98-en",
		"text": "internal"
	},
	"dcp-99-en": {
		"id": "dcp-99-en",
		"text": "intolerable"
	},
	"dcp-100-en": {
		"id": "dcp-100-en",
		"text": "iron"
	},
	"dcp-101-en": {
		"id": "dcp-101-en",
		"text": "itchy"
	},
	"dcp-102-en": {
		"id": "dcp-102-en",
		"text": "lame"
	},
	"dcp-103-en": {
		"id": "dcp-103-en",
		"text": "legal"
	},
	"dcp-104-en": {
		"id": "dcp-104-en",
		"text": "lightweight"
	},
	"dcp-105-en": {
		"id": "dcp-105-en",
		"text": "logical"
	},
	"dcp-106-en": {
		"id": "dcp-106-en",
		"text": "loud"
	},
	"dcp-107-en": {
		"id": "dcp-107-en",
		"text": "luminous"
	},
	"dcp-108-en": {
		"id": "dcp-108-en",
		"text": "luxurious"
	},
	"dcp-109-en": {
		"id": "dcp-109-en",
		"text": "magical"
	},
	"dcp-110-en": {
		"id": "dcp-110-en",
		"text": "masculine"
	},
	"dcp-111-en": {
		"id": "dcp-111-en",
		"text": "mechanical"
	},
	"dcp-112-en": {
		"id": "dcp-112-en",
		"text": "medical"
	},
	"dcp-113-en": {
		"id": "dcp-113-en",
		"text": "melodious"
	},
	"dcp-114-en": {
		"id": "dcp-114-en",
		"text": "mental"
	},
	"dcp-115-en": {
		"id": "dcp-115-en",
		"text": "metallic"
	},
	"dcp-116-en": {
		"id": "dcp-116-en",
		"text": "modest"
	},
	"dcp-117-en": {
		"id": "dcp-117-en",
		"text": "modular"
	},
	"dcp-118-en": {
		"id": "dcp-118-en",
		"text": "motionless"
	},
	"dcp-119-en": {
		"id": "dcp-119-en",
		"text": "motley"
	},
	"dcp-120-en": {
		"id": "dcp-120-en",
		"text": "muffled"
	},
	"dcp-121-en": {
		"id": "dcp-121-en",
		"text": "musical"
	},
	"dcp-122-en": {
		"id": "dcp-122-en",
		"text": "naked"
	},
	"dcp-123-en": {
		"id": "dcp-123-en",
		"text": "noble"
	},
	"dcp-124-en": {
		"id": "dcp-124-en",
		"text": "non-stop"
	},
	"dcp-125-en": {
		"id": "dcp-125-en",
		"text": "obsolete"
	},
	"dcp-126-en": {
		"id": "dcp-126-en",
		"text": "opaque"
	},
	"dcp-127-en": {
		"id": "dcp-127-en",
		"text": "orange"
	},
	"dcp-128-en": {
		"id": "dcp-128-en",
		"text": "outdoor"
	},
	"dcp-129-en": {
		"id": "dcp-129-en",
		"text": "overrated"
	},
	"dcp-130-en": {
		"id": "dcp-130-en",
		"text": "painful"
	},
	"dcp-131-en": {
		"id": "dcp-131-en",
		"text": "paired"
	},
	"dcp-132-en": {
		"id": "dcp-132-en",
		"text": "permanent"
	},
	"dcp-133-en": {
		"id": "dcp-133-en",
		"text": "philosophical"
	},
	"dcp-134-en": {
		"id": "dcp-134-en",
		"text": "physical"
	},
	"dcp-135-en": {
		"id": "dcp-135-en",
		"text": "pink"
	},
	"dcp-136-en": {
		"id": "dcp-136-en",
		"text": "pleasing"
	},
	"dcp-137-en": {
		"id": "dcp-137-en",
		"text": "pointy"
	},
	"dcp-138-en": {
		"id": "dcp-138-en",
		"text": "problematic"
	},
	"dcp-139-en": {
		"id": "dcp-139-en",
		"text": "professional"
	},
	"dcp-140-en": {
		"id": "dcp-140-en",
		"text": "public"
	},
	"dcp-141-en": {
		"id": "dcp-141-en",
		"text": "pungent"
	},
	"dcp-142-en": {
		"id": "dcp-142-en",
		"text": "purple"
	},
	"dcp-143-en": {
		"id": "dcp-143-en",
		"text": "quiet"
	},
	"dcp-144-en": {
		"id": "dcp-144-en",
		"text": "rebellious"
	},
	"dcp-145-en": {
		"id": "dcp-145-en",
		"text": "rechargeable"
	},
	"dcp-146-en": {
		"id": "dcp-146-en",
		"text": "red"
	},
	"dcp-147-en": {
		"id": "dcp-147-en",
		"text": "regular"
	},
	"dcp-148-en": {
		"id": "dcp-148-en",
		"text": "religious"
	},
	"dcp-149-en": {
		"id": "dcp-149-en",
		"text": "resort"
	},
	"dcp-150-en": {
		"id": "dcp-150-en",
		"text": "restraining"
	},
	"dcp-151-en": {
		"id": "dcp-151-en",
		"text": "rigid"
	},
	"dcp-152-en": {
		"id": "dcp-152-en",
		"text": "romantic"
	},
	"dcp-153-en": {
		"id": "dcp-153-en",
		"text": "roomy"
	},
	"dcp-154-en": {
		"id": "dcp-154-en",
		"text": "rough"
	},
	"dcp-155-en": {
		"id": "dcp-155-en",
		"text": "round"
	},
	"dcp-156-en": {
		"id": "dcp-156-en",
		"text": "rubbery"
	},
	"dcp-157-en": {
		"id": "dcp-157-en",
		"text": "rustling"
	},
	"dcp-158-en": {
		"id": "dcp-158-en",
		"text": "safe"
	},
	"dcp-159-en": {
		"id": "dcp-159-en",
		"text": "sassy"
	},
	"dcp-160-en": {
		"id": "dcp-160-en",
		"text": "savory"
	},
	"dcp-161-en": {
		"id": "dcp-161-en",
		"text": "scary"
	},
	"dcp-162-en": {
		"id": "dcp-162-en",
		"text": "seductive"
	},
	"dcp-163-en": {
		"id": "dcp-163-en",
		"text": "sexy"
	},
	"dcp-164-en": {
		"id": "dcp-164-en",
		"text": "shiny"
	},
	"dcp-165-en": {
		"id": "dcp-165-en",
		"text": "short"
	},
	"dcp-166-en": {
		"id": "dcp-166-en",
		"text": "shy"
	},
	"dcp-167-en": {
		"id": "dcp-167-en",
		"text": "silent"
	},
	"dcp-168-en": {
		"id": "dcp-168-en",
		"text": "simple"
	},
	"dcp-169-en": {
		"id": "dcp-169-en",
		"text": "skinny"
	},
	"dcp-170-en": {
		"id": "dcp-170-en",
		"text": "slippery"
	},
	"dcp-171-en": {
		"id": "dcp-171-en",
		"text": "smart"
	},
	"dcp-172-en": {
		"id": "dcp-172-en",
		"text": "smooth"
	},
	"dcp-173-en": {
		"id": "dcp-173-en",
		"text": "soft"
	},
	"dcp-174-en": {
		"id": "dcp-174-en",
		"text": "sour"
	},
	"dcp-175-en": {
		"id": "dcp-175-en",
		"text": "sparkling"
	},
	"dcp-176-en": {
		"id": "dcp-176-en",
		"text": "spicy"
	},
	"dcp-177-en": {
		"id": "dcp-177-en",
		"text": "square"
	},
	"dcp-178-en": {
		"id": "dcp-178-en",
		"text": "standard"
	},
	"dcp-179-en": {
		"id": "dcp-179-en",
		"text": "sticky"
	},
	"dcp-180-en": {
		"id": "dcp-180-en",
		"text": "stinky"
	},
	"dcp-181-en": {
		"id": "dcp-181-en",
		"text": "sudden"
	},
	"dcp-182-en": {
		"id": "dcp-182-en",
		"text": "summertime"
	},
	"dcp-183-en": {
		"id": "dcp-183-en",
		"text": "superstitious"
	},
	"dcp-184-en": {
		"id": "dcp-184-en",
		"text": "sweet"
	},
	"dcp-185-en": {
		"id": "dcp-185-en",
		"text": "synthetic"
	},
	"dcp-186-en": {
		"id": "dcp-186-en",
		"text": "talkative"
	},
	"dcp-187-en": {
		"id": "dcp-187-en",
		"text": "tall"
	},
	"dcp-188-en": {
		"id": "dcp-188-en",
		"text": "technological"
	},
	"dcp-189-en": {
		"id": "dcp-189-en",
		"text": "temporary"
	},
	"dcp-190-en": {
		"id": "dcp-190-en",
		"text": "textured"
	},
	"dcp-191-en": {
		"id": "dcp-191-en",
		"text": "thin"
	},
	"dcp-192-en": {
		"id": "dcp-192-en",
		"text": "thoughtful"
	},
	"dcp-193-en": {
		"id": "dcp-193-en",
		"text": "touchable"
	},
	"dcp-194-en": {
		"id": "dcp-194-en",
		"text": "transparent"
	},
	"dcp-195-en": {
		"id": "dcp-195-en",
		"text": "underground"
	},
	"dcp-196-en": {
		"id": "dcp-196-en",
		"text": "urban"
	},
	"dcp-197-en": {
		"id": "dcp-197-en",
		"text": "verbal"
	},
	"dcp-198-en": {
		"id": "dcp-198-en",
		"text": "vibrant"
	},
	"dcp-199-en": {
		"id": "dcp-199-en",
		"text": "virtual"
	},
	"dcp-200-en": {
		"id": "dcp-200-en",
		"text": "voluntary"
	},
	"dcp-201-en": {
		"id": "dcp-201-en",
		"text": "warm"
	},
	"dcp-202-en": {
		"id": "dcp-202-en",
		"text": "wearable"
	},
	"dcp-203-en": {
		"id": "dcp-203-en",
		"text": "western"
	},
	"dcp-204-en": {
		"id": "dcp-204-en",
		"text": "white"
	},
	"dcp-205-en": {
		"id": "dcp-205-en",
		"text": "wintertime"
	},
	"dcp-206-en": {
		"id": "dcp-206-en",
		"text": "wireless"
	},
	"dcp-207-en": {
		"id": "dcp-207-en",
		"text": "wise"
	},
	"dcp-208-en": {
		"id": "dcp-208-en",
		"text": "wooden"
	},
	"dcp-209-en": {
		"id": "dcp-209-en",
		"text": "written"
	},
	"dcp-210-en": {
		"id": "dcp-210-en",
		"text": "yellow"
	}
}
