{
  "theme-01": {
    "id": "theme-01",
    "text": "a city",
    "description": ""
  },
  "theme-02": {
    "id": "theme-02",
    "text": "a quality or flaw",
    "description": "not every adjective is a quality or flaw"
  },
  "theme-03": {
    "id": "theme-03",
    "text": "a type of clothing",
    "description": "shoes and accessories are allowed"
  },
  "theme-04": {
    "id": "theme-04",
    "text": "a verb",
    "description": "single word only"
  },
  "theme-05": {
    "id": "theme-05",
    "text": "a geometrical shape",
    "description": ""
  },
  "theme-06": {
    "id": "theme-06",
    "text": "an edible item",
    "description": "if you'd eat it's edible"
  },
  "theme-07": {
    "id": "theme-07",
    "text": "a musical instrument",
    "description": ""
  },
  "theme-08": {
    "id": "theme-08",
    "text": "a word beginning with \"B\"",
    "description": ""
  },
  "theme-09": {
    "id": "theme-09",
    "text": "a celebrity (living)",
    "description": ""
  },
  "theme-10": {
    "id": "theme-10",
    "text": "an adjective",
    "description": ""
  },
  "theme-11": {
    "id": "theme-11",
    "text": "a hobby or pastime",
    "description": ""
  },
  "theme-12": {
    "id": "theme-12",
    "text": "an insect",
    "description": ""
  },
  "theme-13": {
    "id": "theme-13",
    "text": "a game title (all types)",
    "description": ""
  },
  "theme-14": {
    "id": "theme-14",
    "text": "something usually found in a kitchen",
    "description": ""
  },
  "theme-15": {
    "id": "theme-15",
    "text": "a made up word",
    "description": "only up to three syllables allowed"
  },
  "theme-16": {
    "id": "theme-16",
    "text": "a word beginning with \"P\"",
    "description": ""
  },
  "theme-17": {
    "id": "theme-17",
    "text": "a word of 5 or fewer letters",
    "description": ""
  },
  "theme-18": {
    "id": "theme-18",
    "text": "a school supply",
    "description": ""
  },
  "theme-19": {
    "id": "theme-19",
    "text": "a weapon",
    "description": "if you can kill someone or something, it's a weapon"
  },
  "theme-20": {
    "id": "theme-20",
    "text": "a tourist attraction",
    "description": "do not use a city or country name"
  },
  "theme-21": {
    "id": "theme-21",
    "text": "a fantastical or mythological create or monster",
    "description": "cartoon characters are allowed as long are they are not a common animal"
  },
  "theme-22": {
    "id": "theme-22",
    "text": "a swear or an insult",
    "description": ""
  },
  "theme-23": {
    "id": "theme-23",
    "text": "a public or governmental institution",
    "description": ""
  },
  "theme-24": {
    "id": "theme-24",
    "text": "a word of 8 or more letters",
    "description": ""
  },
  "theme-25": {
    "id": "theme-25",
    "text": "something usually found in a bathroom",
    "description": ""
  },
  "theme-26": {
    "id": "theme-26",
    "text": "a book title",
    "description": ""
  },
  "theme-27": {
    "id": "theme-27",
    "text": "something to do with the old west",
    "description": ""
  },
  "theme-28": {
    "id": "theme-28",
    "text": "a vehicle or a method of transportation",
    "description": ""
  },
  "theme-29": {
    "id": "theme-29",
    "text": "a historical figure (deceased)",
    "description": ""
  },
  "theme-30": {
    "id": "theme-30",
    "text": "an animal",
    "description": ""
  },
  "theme-31": {
    "id": "theme-31",
    "text": "a possible cause of death",
    "description": "something believable"
  },
  "theme-32": {
    "id": "theme-32",
    "text": "a company or a type of business (non-fictional)",
    "description": ""
  },
  "theme-33": {
    "id": "theme-33",
    "text": "a word beginning with \"A\"",
    "description": ""
  },
  "theme-34": {
    "id": "theme-34",
    "text": "a color",
    "description": ""
  },
  "theme-35": {
    "id": "theme-35",
    "text": "a date",
    "description": "only numbers, month names, holidays, or references to days of the week ('second sunday of june)"
  },
  "theme-36": {
    "id": "theme-36",
    "text": "a drug or a type of medicine",
    "description": ""
  },
  "theme-37": {
    "id": "theme-37",
    "text": "a movie title",
    "description": ""
  },
  "theme-38": {
    "id": "theme-38",
    "text": "a musician or musical group",
    "description": ""
  },
  "theme-39": {
    "id": "theme-39",
    "text": "a disease",
    "description": ""
  },
  "theme-40": {
    "id": "theme-40",
    "text": "an onomatopoeia",
    "description": ""
  },
  "theme-41": {
    "id": "theme-41",
    "text": "a body part of a internal organ",
    "description": ""
  },
  "theme-42": {
    "id": "theme-42",
    "text": "a country",
    "description": ""
  },
  "theme-43": {
    "id": "theme-43",
    "text": "a fictional character",
    "description": ""
  },
  "theme-44": {
    "id": "theme-44",
    "text": "a meteorological phenomenon or natural disaster",
    "description": ""
  },
  "theme-45": {
    "id": "theme-45",
    "text": "a plant or vegetable",
    "description": ""
  },
  "theme-46": {
    "id": "theme-46",
    "text": "a profession or occupation",
    "description": ""
  },
  "theme-47": {
    "id": "theme-47",
    "text": "something found in a hospital",
    "description": ""
  },
  "theme-48": {
    "id": "theme-48",
    "text": "a television series",
    "description": ""
  },
  "theme-49": {
    "id": "theme-49",
    "text": "a sport",
    "description": ""
  },
  "theme-50": {
    "id": "theme-50",
    "text": "a song title",
    "description": ""
  },
  "theme-51": {
    "id": "theme-51",
    "text": "a type of alcohol",
    "description": ""
  },
  "theme-52": {
    "id": "theme-52",
    "text": "a recipe or cooked dish",
    "description": ""
  },
  "theme-53": {
    "id": "theme-53",
    "text": "a unit of measurement",
    "description": ""
  },
  "theme-54": {
    "id": "theme-54",
    "text": "a band",
    "description": ""
  },
  "theme-55": {
    "id": "theme-55",
    "text": "a tv show",
    "description": ""
  },
  "theme-56": {
    "id": "theme-56",
    "text": "a telenovela or reality show",
    "description": ""
  },
  "theme-57": {
    "id": "theme-57",
    "text": "a word beginning with \"M\"",
    "description": ""
  },
  "theme-58": {
    "id": "theme-58",
    "text": "a phone app",
    "description": ""
  },
  "theme-59": {
    "id": "theme-59",
    "text": "a super hero",
    "description": ""
  },
  "theme-60": {
    "id": "theme-60",
    "text": "a feeling",
    "description": ""
  },
  "theme-61": {
    "id": "theme-61",
    "text": "a word beginning with the first letter of your name",
    "description": ""
  },
  "theme-62": {
    "id": "theme-62",
    "text": "a relative or family member",
    "description": ""
  },
  "theme-63": {
    "id": "theme-63",
    "text": "a word beginning with \"Y\"",
    "description": ""
  },
  "theme-64": {
    "id": "theme-64",
    "text": "a computer keyboard key",
    "description": ""
  }
}
