{
  "wsd-1-pt": {
    "id": "wsd-1-pt",
    "text": "aconchegante"
  },
  "wsd-2-pt": {
    "id": "wsd-2-pt",
    "text": "afetuoso"
  },
  "wsd-3-pt": {
    "id": "wsd-3-pt",
    "text": "afogando"
  },
  "wsd-4-pt": {
    "id": "wsd-4-pt",
    "text": "alegre"
  },
  "wsd-5-pt": {
    "id": "wsd-5-pt",
    "text": "alto"
  },
  "wsd-6-pt": {
    "id": "wsd-6-pt",
    "text": "amigável"
  },
  "wsd-7-pt": {
    "id": "wsd-7-pt",
    "text": "arrastado"
  },
  "wsd-8-pt": {
    "id": "wsd-8-pt",
    "text": "artístico"
  },
  "wsd-9-pt": {
    "id": "wsd-9-pt",
    "text": "assustado"
  },
  "wsd-10-pt": {
    "id": "wsd-10-pt",
    "text": "assustador"
  },
  "wsd-11-pt": {
    "id": "wsd-11-pt",
    "text": "aterrorizado"
  },
  "wsd-12-pt": {
    "id": "wsd-12-pt",
    "text": "bagunçado"
  },
  "wsd-13-pt": {
    "id": "wsd-13-pt",
    "text": "bêbado"
  },
  "wsd-14-pt": {
    "id": "wsd-14-pt",
    "text": "belo"
  },
  "wsd-15-pt": {
    "id": "wsd-15-pt",
    "text": "bonita"
  },
  "wsd-16-pt": {
    "id": "wsd-16-pt",
    "text": "brilhante"
  },
  "wsd-17-pt": {
    "id": "wsd-17-pt",
    "text": "brilhante"
  },
  "wsd-18-pt": {
    "id": "wsd-18-pt",
    "text": "brincalhão"
  },
  "wsd-19-pt": {
    "id": "wsd-19-pt",
    "text": "caindo"
  },
  "wsd-20-pt": {
    "id": "wsd-20-pt",
    "text": "caipira"
  },
  "wsd-21-pt": {
    "id": "wsd-21-pt",
    "text": "caro"
  },
  "wsd-22-pt": {
    "id": "wsd-22-pt",
    "text": "celestial"
  },
  "wsd-23-pt": {
    "id": "wsd-23-pt",
    "text": "chique"
  },
  "wsd-24-pt": {
    "id": "wsd-24-pt",
    "text": "choroso"
  },
  "wsd-25-pt": {
    "id": "wsd-25-pt",
    "text": "confuso"
  },
  "wsd-26-pt": {
    "id": "wsd-26-pt",
    "text": "correndo"
  },
  "wsd-27-pt": {
    "id": "wsd-27-pt",
    "text": "dançarino"
  },
  "wsd-28-pt": {
    "id": "wsd-28-pt",
    "text": "delicioso"
  },
  "wsd-29-pt": {
    "id": "wsd-29-pt",
    "text": "derretido"
  },
  "wsd-30-pt": {
    "id": "wsd-30-pt",
    "text": "desajeitado"
  },
  "wsd-31-pt": {
    "id": "wsd-31-pt",
    "text": "dinâmico"
  },
  "wsd-32-pt": {
    "id": "wsd-32-pt",
    "text": "disco"
  },
  "wsd-33-pt": {
    "id": "wsd-33-pt",
    "text": "doce"
  },
  "wsd-34-pt": {
    "id": "wsd-34-pt",
    "text": "doente"
  },
  "wsd-35-pt": {
    "id": "wsd-35-pt",
    "text": "dorminhoco"
  },
  "wsd-36-pt": {
    "id": "wsd-36-pt",
    "text": "dramático"
  },
  "wsd-37-pt": {
    "id": "wsd-37-pt",
    "text": "elegante"
  },
  "wsd-38-pt": {
    "id": "wsd-38-pt",
    "text": "encantador"
  },
  "wsd-39-pt": {
    "id": "wsd-39-pt",
    "text": "energético"
  },
  "wsd-40-pt": {
    "id": "wsd-40-pt",
    "text": "enrugado"
  },
  "wsd-41-pt": {
    "id": "wsd-41-pt",
    "text": "entusiástico"
  },
  "wsd-42-pt": {
    "id": "wsd-42-pt",
    "text": "escorregadio"
  },
  "wsd-43-pt": {
    "id": "wsd-43-pt",
    "text": "esmagador"
  },
  "wsd-44-pt": {
    "id": "wsd-44-pt",
    "text": "estiloso"
  },
  "wsd-45-pt": {
    "id": "wsd-45-pt",
    "text": "estranho"
  },
  "wsd-46-pt": {
    "id": "wsd-46-pt",
    "text": "estressado"
  },
  "wsd-47-pt": {
    "id": "wsd-47-pt",
    "text": "faminto"
  },
  "wsd-48-pt": {
    "id": "wsd-48-pt",
    "text": "fantasmagórico"
  },
  "wsd-49-pt": {
    "id": "wsd-49-pt",
    "text": "fedido"
  },
  "wsd-50-pt": {
    "id": "wsd-50-pt",
    "text": "feio"
  },
  "wsd-51-pt": {
    "id": "wsd-51-pt",
    "text": "feliz"
  },
  "wsd-52-pt": {
    "id": "wsd-52-pt",
    "text": "flexível"
  },
  "wsd-53-pt": {
    "id": "wsd-53-pt",
    "text": "fofinho"
  },
  "wsd-54-pt": {
    "id": "wsd-54-pt",
    "text": "fofo"
  },
  "wsd-55-pt": {
    "id": "wsd-55-pt",
    "text": "forte"
  },
  "wsd-56-pt": {
    "id": "wsd-56-pt",
    "text": "futurista"
  },
  "wsd-57-pt": {
    "id": "wsd-57-pt",
    "text": "gasoso"
  },
  "wsd-58-pt": {
    "id": "wsd-58-pt",
    "text": "gordo"
  },
  "wsd-59-pt": {
    "id": "wsd-59-pt",
    "text": "grávida"
  },
  "wsd-60-pt": {
    "id": "wsd-60-pt",
    "text": "grosseiro"
  },
  "wsd-61-pt": {
    "id": "wsd-61-pt",
    "text": "imundo"
  },
  "wsd-62-pt": {
    "id": "wsd-62-pt",
    "text": "inchado"
  },
  "wsd-63-pt": {
    "id": "wsd-63-pt",
    "text": "irritante"
  },
  "wsd-64-pt": {
    "id": "wsd-64-pt",
    "text": "legal"
  },
  "wsd-65-pt": {
    "id": "wsd-65-pt",
    "text": "leve"
  },
  "wsd-66-pt": {
    "id": "wsd-66-pt",
    "text": "lixo"
  },
  "wsd-67-pt": {
    "id": "wsd-67-pt",
    "text": "maduro"
  },
  "wsd-68-pt": {
    "id": "wsd-68-pt",
    "text": "mágico"
  },
  "wsd-69-pt": {
    "id": "wsd-69-pt",
    "text": "magro"
  },
  "wsd-70-pt": {
    "id": "wsd-70-pt",
    "text": "mal-humorado"
  },
  "wsd-71-pt": {
    "id": "wsd-71-pt",
    "text": "maluco"
  },
  "wsd-72-pt": {
    "id": "wsd-72-pt",
    "text": "mau"
  },
  "wsd-73-pt": {
    "id": "wsd-73-pt",
    "text": "musculoso"
  },
  "wsd-74-pt": {
    "id": "wsd-74-pt",
    "text": "musical"
  },
  "wsd-75-pt": {
    "id": "wsd-75-pt",
    "text": "nerd"
  },
  "wsd-76-pt": {
    "id": "wsd-76-pt",
    "text": "nobre"
  },
  "wsd-77-pt": {
    "id": "wsd-77-pt",
    "text": "pacífico"
  },
  "wsd-78-pt": {
    "id": "wsd-78-pt",
    "text": "pegajoso"
  },
  "wsd-79-pt": {
    "id": "wsd-79-pt",
    "text": "pequeno"
  },
  "wsd-80-pt": {
    "id": "wsd-80-pt",
    "text": "peralta"
  },
  "wsd-81-pt": {
    "id": "wsd-81-pt",
    "text": "perverso"
  },
  "wsd-82-pt": {
    "id": "wsd-82-pt",
    "text": "pesado"
  },
  "wsd-83-pt": {
    "id": "wsd-83-pt",
    "text": "podre"
  },
  "wsd-84-pt": {
    "id": "wsd-84-pt",
    "text": "pulando"
  },
  "wsd-85-pt": {
    "id": "wsd-85-pt",
    "text": "quebrado"
  },
  "wsd-86-pt": {
    "id": "wsd-86-pt",
    "text": "rabugento"
  },
  "wsd-87-pt": {
    "id": "wsd-87-pt",
    "text": "rápido"
  },
  "wsd-88-pt": {
    "id": "wsd-88-pt",
    "text": "rápido"
  },
  "wsd-89-pt": {
    "id": "wsd-89-pt",
    "text": "rastejante"
  },
  "wsd-90-pt": {
    "id": "wsd-90-pt",
    "text": "relaxando"
  },
  "wsd-91-pt": {
    "id": "wsd-91-pt",
    "text": "retrô"
  },
  "wsd-92-pt": {
    "id": "wsd-92-pt",
    "text": "rindo"
  },
  "wsd-93-pt": {
    "id": "wsd-93-pt",
    "text": "robótico"
  },
  "wsd-94-pt": {
    "id": "wsd-94-pt",
    "text": "roliço"
  },
  "wsd-95-pt": {
    "id": "wsd-95-pt",
    "text": "romântico"
  },
  "wsd-96-pt": {
    "id": "wsd-96-pt",
    "text": "saltitante"
  },
  "wsd-97-pt": {
    "id": "wsd-97-pt",
    "text": "tóxico"
  },
  "wsd-98-pt": {
    "id": "wsd-98-pt",
    "text": "triste"
  },
  "wsd-99-pt": {
    "id": "wsd-99-pt",
    "text": "voador"
  },
  "wsd-100-pt": {
    "id": "wsd-100-pt",
    "text": "zangado"
  }
}
